onesignal/__init__.py
onesignal/core.py
onesignal/device_notification.py
onesignal/errors.py
onesignal/filter.py
onesignal/filter_notification.py
onesignal/notification.py
onesignal/segment_notification.py
onesignal/utils.py
onesignal_client-0.0.2.dist-info/LICENSE
onesignal_client-0.0.2.dist-info/METADATA
onesignal_client-0.0.2.dist-info/WHEEL
onesignal_client-0.0.2.dist-info/top_level.txt
onesignal_client-0.0.2.dist-info/RECORD
