Metadata-Version: 2.1
Name: onesignal-client
Version: 0.0.2
Summary: OneSignal API wrapper
Home-page: https://github.com/radimsuckr/onesignal-client
Author: Radim Sückr
Author-email: contact@radimsuckr.cz
License: MIT
Platform: UNKNOWN
Classifier: Intended Audience :: Developers
Classifier: License :: OSI Approved :: MIT License
Classifier: Operating System :: OS Independent
Classifier: Programming Language :: Python :: 3.6
Classifier: Programming Language :: Python :: 3.7
Classifier: Topic :: Internet :: WWW/HTTP
Classifier: Topic :: Software Development :: Libraries :: Python Modules
Requires-Dist: requests
